[{
    "Website": "https://www.coachella.com/",
    "Festival Name": "Coachella",
    "Dates": "April 14-16, April 21-23",
    "Location": "Indio, CA",
    "Camping": "Yes"
}, {
    "Website": "lightninginabottle.org",
    "Festival Name": "Lightning in a Bottle",
    "Dates": "May 24-May 29",
    "Location": "Bradley, CA",
    "Camping": "Yes"
}, {
    "Website": "sfoutsidelands.org",
    "Festival Name": "Outsidelands",
    "Dates": "August 11–13",
    "Location": "San Francisco, CA",
    "Camping": "No"
}, {
    "Website": "crssdfest.com",
    "Festival Name": "CRSSD",
    "Dates": "September 30-October 1",
    "Location": "San Diego, CA",
    "Camping": "No"
}, {
    "Website": "stagecoachfest.com",
    "Festival Name": "Stagecoach",
    "Dates": "April 28–Apr 30",
    "Location": "Indio, CA",
    "Camping": "Yes"
}, {
    "Website": "fyffest.com",
    "Festival Name": "FYF",
    "Dates": "July 22-23",
    "Location": "Los Angeles, CA",
    "Camping": "No"
}, {
    "Website": "symbiosisgathering.com",
    "Festival Name": "Symbiosis",
    "Dates": "September 22-25",
    "Location": "Oakdale, CA",
    "Camping": "Yes"
}, {
    "Website": "reggaeontheriver.com",
    "Festival Name": "Reggae on the River",
    "Dates": "August 3-6",
    "Location": "Garberville, CA",
    "Camping": "Yes"
}, {
    "Website": "Kaaboodelmar.com",
    "Festival Name": "Kaaboo",
    "Dates": "Sept 15-17",
    "Location": "Del Mar, CA",
    "Camping": "No"
}, {
    "Website": "hardfest.com",
    "Festival Name": "Hard Summer",
    "Dates": "August 5-6",
    "Location": "Los Angeles, CA",
    "Camping": "No"
}, {
    "Website": "snowglobemusicfestival.com/",
    "Festival Name": "Snowglobe",
    "Dates": "December 29-31",
    "Location": "South Lake Tahoe, CA",
    "Camping": "No"
}, {
    "Website": "beyondwonderland.com/",
    "Festival Name": "Beyond Wonderland",
    "Dates": "March 24-25",
    "Location": "San Bernardino, CA",
    "Camping": "No"
}, {
    "Website": "https://www.desertheartsfestival.com/",
    "Festival Name": "Desert Hearts",
    "Dates": "March 31-April 3",
    "Location": "Warner Springs, CA",
    "Camping": "Yes"
}]